{
    "match_details": {
        "fixture": "Gasogi United vs Kiyovu Sports",
        "match_id": "1275483",
        "match_date": "Feb. 24, 2025, 1 p.m.",
        "venue": null,
        "city": "Kigali",
        "league_id": "405",
        "home_team_name": "Gasogi United",
        "away_team_name": "Kiyovu Sports",
        "home_team_logo": "https://media.api-sports.io/football/teams/7574.png",
        "away_team_logo": "https://media.api-sports.io/football/teams/5317.png",
        "home_team_id": "7574",
        "away_team_id": "5317"
    },
    "weather": {
        "temperature": 26.03,
        "feels_like": 26.03,
        "humidity": 44,
        "weather_description": "Scattered clouds",
        "wind_speed": 3.4,
        "rain": 0
    },
    "odds": {
        "NordicBet": {
            "Match Winner": [
                {
                    "value": "Home",
                    "odd": "2.05"
                },
                {
                    "value": "Draw",
                    "odd": "3.35"
                },
                {
                    "value": "Away",
                    "odd": "3.15"
                }
            ],
            "Home/Away": [
                {
                    "value": "Home",
                    "odd": "1.53"
                },
                {
                    "value": "Away",
                    "odd": "2.33"
                }
            ],
            "Goals Over/Under": [
                {
                    "value": "Over 1.5",
                    "odd": "1.48"
                },
                {
                    "value": "Under 1.5",
                    "odd": "2.46"
                },
                {
                    "value": "Over 2.5",
                    "odd": "2.42"
                },
                {
                    "value": "Under 2.5",
                    "odd": "1.50"
                },
                {
                    "value": "Over 3.5",
                    "odd": "4.60"
                },
                {
                    "value": "Under 3.5",
                    "odd": "1.16"
                }
            ],
            "Both Teams Score": [
                {
                    "value": "Yes",
                    "odd": "2.17"
                },
                {
                    "value": "No",
                    "odd": "1.62"
                }
            ],
            "Double Chance": [
                {
                    "value": "Home/Draw",
                    "odd": "1.28"
                },
                {
                    "value": "Home/Away",
                    "odd": "1.26"
                },
                {
                    "value": "Draw/Away",
                    "odd": "1.61"
                }
            ],
            "Total - Home": [
                {
                    "value": "Over 1.5",
                    "odd": "2.50"
                },
                {
                    "value": "Under 1.5",
                    "odd": "1.47"
                }
            ],
            "Total - Away": [
                {
                    "value": "Over 0.5",
                    "odd": "1.56"
                },
                {
                    "value": "Under 0.5",
                    "odd": "2.27"
                }
            ]
        }
    },
    "average_league_goals": {},
    "head_to_head_data": null,
    "head_to_head_statistics_with_home_at_home_and_away_at_away": [],
    "home_run": [],
    "away_run": [],
    "home_team_player_ratings_sesason": {},
    "away_team_player_ratings_sesason": {},
    "home_last_five_fixture_and_stats": null,
    "away_last_five_fixture_and_stats": null,
    "predictions": [
        {
            "predictions": {
                "winner": {
                    "id": 7574,
                    "name": "Gasogi United",
                    "comment": "Win or draw"
                },
                "win_or_draw": true,
                "under_over": null,
                "goals": {
                    "home": "-2.5",
                    "away": "-1.5"
                },
                "advice": "Double chance : Gasogi United or draw",
                "percent": {
                    "home": "45%",
                    "draw": "45%",
                    "away": "10%"
                }
            },
            "league": {
                "id": 405,
                "name": "National Soccer League",
                "country": "Rwanda",
                "logo": "https://media.api-sports.io/football/leagues/405.png",
                "flag": "https://media.api-sports.io/flags/rw.svg",
                "season": 2024
            },
            "teams": {
                "home": {
                    "id": 7574,
                    "name": "Gasogi United",
                    "logo": "https://media.api-sports.io/football/teams/7574.png",
                    "last_5": {
                        "played": 5,
                        "form": "13%",
                        "att": "21%",
                        "def": "36%",
                        "goals": {
                            "for": {
                                "total": 3,
                                "average": "0.6"
                            },
                            "against": {
                                "total": 9,
                                "average": "1.8"
                            }
                        }
                    },
                    "league": {
                        "form": "WWDLDLWLWDDWDLLLD",
                        "fixtures": {
                            "played": {
                                "home": 8,
                                "away": 9,
                                "total": 17
                            },
                            "wins": {
                                "home": 2,
                                "away": 3,
                                "total": 5
                            },
                            "draws": {
                                "home": 3,
                                "away": 3,
                                "total": 6
                            },
                            "loses": {
                                "home": 3,
                                "away": 3,
                                "total": 6
                            }
                        },
                        "goals": {
                            "for": {
                                "total": {
                                    "home": 10,
                                    "away": 8,
                                    "total": 18
                                },
                                "average": {
                                    "home": "1.3",
                                    "away": "0.9",
                                    "total": "1.1"
                                },
                                "minute": {
                                    "0-15": {
                                        "total": 1,
                                        "percentage": "7.69%"
                                    },
                                    "16-30": {
                                        "total": null,
                                        "percentage": null
                                    },
                                    "31-45": {
                                        "total": 3,
                                        "percentage": "23.08%"
                                    },
                                    "46-60": {
                                        "total": 4,
                                        "percentage": "30.77%"
                                    },
                                    "61-75": {
                                        "total": 2,
                                        "percentage": "15.38%"
                                    },
                                    "76-90": {
                                        "total": 3,
                                        "percentage": "23.08%"
                                    },
                                    "91-105": {
                                        "total": null,
                                        "percentage": null
                                    },
                                    "106-120": {
                                        "total": null,
                                        "percentage": null
                                    }
                                },
                                "under_over": {
                                    "0.5": {
                                        "over": 10,
                                        "under": 7
                                    },
                                    "1.5": {
                                        "over": 5,
                                        "under": 12
                                    },
                                    "2.5": {
                                        "over": 2,
                                        "under": 15
                                    },
                                    "3.5": {
                                        "over": 1,
                                        "under": 16
                                    },
                                    "4.5": {
                                        "over": 0,
                                        "under": 17
                                    }
                                }
                            },
                            "against": {
                                "total": {
                                    "home": 9,
                                    "away": 11,
                                    "total": 20
                                },
                                "average": {
                                    "home": "1.1",
                                    "away": "1.2",
                                    "total": "1.2"
                                },
                                "minute": {
                                    "0-15": {
                                        "total": 2,
                                        "percentage": "14.29%"
                                    },
                                    "16-30": {
                                        "total": 1,
                                        "percentage": "7.14%"
                                    },
                                    "31-45": {
                                        "total": 1,
                                        "percentage": "7.14%"
                                    },
                                    "46-60": {
                                        "total": 2,
                                        "percentage": "14.29%"
                                    },
                                    "61-75": {
                                        "total": 3,
                                        "percentage": "21.43%"
                                    },
                                    "76-90": {
                                        "total": 4,
                                        "percentage": "28.57%"
                                    },
                                    "91-105": {
                                        "total": 1,
                                        "percentage": "7.14%"
                                    },
                                    "106-120": {
                                        "total": null,
                                        "percentage": null
                                    }
                                },
                                "under_over": {
                                    "0.5": {
                                        "over": 11,
                                        "under": 6
                                    },
                                    "1.5": {
                                        "over": 7,
                                        "under": 10
                                    },
                                    "2.5": {
                                        "over": 2,
                                        "under": 15
                                    },
                                    "3.5": {
                                        "over": 0,
                                        "under": 17
                                    },
                                    "4.5": {
                                        "over": 0,
                                        "under": 17
                                    }
                                }
                            }
                        },
                        "biggest": {
                            "streak": {
                                "wins": 2,
                                "draws": 2,
                                "loses": 3
                            },
                            "wins": {
                                "home": "3-0",
                                "away": "3-4"
                            },
                            "loses": {
                                "home": "1-2",
                                "away": "3-0"
                            },
                            "goals": {
                                "for": {
                                    "home": 3,
                                    "away": 4
                                },
                                "against": {
                                    "home": 2,
                                    "away": 3
                                }
                            }
                        },
                        "clean_sheet": {
                            "home": 2,
                            "away": 4,
                            "total": 6
                        },
                        "failed_to_score": {
                            "home": 2,
                            "away": 5,
                            "total": 7
                        },
                        "penalty": {
                            "scored": {
                                "total": 3,
                                "percentage": "100.00%"
                            },
                            "missed": {
                                "total": 0,
                                "percentage": "0%"
                            },
                            "total": 3
                        },
                        "lineups": [],
                        "cards": {
                            "yellow": {
                                "0-15": {
                                    "total": null,
                                    "percentage": null
                                },
                                "16-30": {
                                    "total": null,
                                    "percentage": null
                                },
                                "31-45": {
                                    "total": null,
                                    "percentage": null
                                },
                                "46-60": {
                                    "total": null,
                                    "percentage": null
                                },
                                "61-75": {
                                    "total": null,
                                    "percentage": null
                                },
                                "76-90": {
                                    "total": null,
                                    "percentage": null
                                },
                                "91-105": {
                                    "total": null,
                                    "percentage": null
                                },
                                "106-120": {
                                    "total": null,
                                    "percentage": null
                                }
                            },
                            "red": {
                                "0-15": {
                                    "total": null,
                                    "percentage": null
                                },
                                "16-30": {
                                    "total": null,
                                    "percentage": null
                                },
                                "31-45": {
                                    "total": null,
                                    "percentage": null
                                },
                                "46-60": {
                                    "total": null,
                                    "percentage": null
                                },
                                "61-75": {
                                    "total": null,
                                    "percentage": null
                                },
                                "76-90": {
                                    "total": null,
                                    "percentage": null
                                },
                                "91-105": {
                                    "total": null,
                                    "percentage": null
                                },
                                "106-120": {
                                    "total": null,
                                    "percentage": null
                                }
                            }
                        }
                    }
                },
                "away": {
                    "id": 5317,
                    "name": "Kiyovu Sports",
                    "logo": "https://media.api-sports.io/football/teams/5317.png",
                    "last_5": {
                        "played": 5,
                        "form": "33%",
                        "att": "43%",
                        "def": "50%",
                        "goals": {
                            "for": {
                                "total": 6,
                                "average": "1.2"
                            },
                            "against": {
                                "total": 7,
                                "average": "1.4"
                            }
                        }
                    },
                    "league": {
                        "form": "WLLLLLLLWDLLDWDLL",
                        "fixtures": {
                            "played": {
                                "home": 10,
                                "away": 7,
                                "total": 17
                            },
                            "wins": {
                                "home": 3,
                                "away": 0,
                                "total": 3
                            },
                            "draws": {
                                "home": 0,
                                "away": 3,
                                "total": 3
                            },
                            "loses": {
                                "home": 7,
                                "away": 4,
                                "total": 11
                            }
                        },
                        "goals": {
                            "for": {
                                "total": {
                                    "home": 13,
                                    "away": 3,
                                    "total": 16
                                },
                                "average": {
                                    "home": "1.3",
                                    "away": "0.4",
                                    "total": "0.9"
                                },
                                "minute": {
                                    "0-15": {
                                        "total": 1,
                                        "percentage": "9.09%"
                                    },
                                    "16-30": {
                                        "total": 2,
                                        "percentage": "18.18%"
                                    },
                                    "31-45": {
                                        "total": 3,
                                        "percentage": "27.27%"
                                    },
                                    "46-60": {
                                        "total": 1,
                                        "percentage": "9.09%"
                                    },
                                    "61-75": {
                                        "total": null,
                                        "percentage": null
                                    },
                                    "76-90": {
                                        "total": 3,
                                        "percentage": "27.27%"
                                    },
                                    "91-105": {
                                        "total": 1,
                                        "percentage": "9.09%"
                                    },
                                    "106-120": {
                                        "total": null,
                                        "percentage": null
                                    }
                                },
                                "under_over": {
                                    "0.5": {
                                        "over": 9,
                                        "under": 8
                                    },
                                    "1.5": {
                                        "over": 5,
                                        "under": 12
                                    },
                                    "2.5": {
                                        "over": 2,
                                        "under": 15
                                    },
                                    "3.5": {
                                        "over": 0,
                                        "under": 17
                                    },
                                    "4.5": {
                                        "over": 0,
                                        "under": 17
                                    }
                                }
                            },
                            "against": {
                                "total": {
                                    "home": 18,
                                    "away": 16,
                                    "total": 34
                                },
                                "average": {
                                    "home": "1.8",
                                    "away": "2.3",
                                    "total": "2.0"
                                },
                                "minute": {
                                    "0-15": {
                                        "total": 3,
                                        "percentage": "10.34%"
                                    },
                                    "16-30": {
                                        "total": 4,
                                        "percentage": "13.79%"
                                    },
                                    "31-45": {
                                        "total": 5,
                                        "percentage": "17.24%"
                                    },
                                    "46-60": {
                                        "total": 6,
                                        "percentage": "20.69%"
                                    },
                                    "61-75": {
                                        "total": 2,
                                        "percentage": "6.90%"
                                    },
                                    "76-90": {
                                        "total": 7,
                                        "percentage": "24.14%"
                                    },
                                    "91-105": {
                                        "total": 2,
                                        "percentage": "6.90%"
                                    },
                                    "106-120": {
                                        "total": null,
                                        "percentage": null
                                    }
                                },
                                "under_over": {
                                    "0.5": {
                                        "over": 15,
                                        "under": 2
                                    },
                                    "1.5": {
                                        "over": 10,
                                        "under": 7
                                    },
                                    "2.5": {
                                        "over": 5,
                                        "under": 12
                                    },
                                    "3.5": {
                                        "over": 4,
                                        "under": 13
                                    },
                                    "4.5": {
                                        "over": 0,
                                        "under": 17
                                    }
                                }
                            }
                        },
                        "biggest": {
                            "streak": {
                                "wins": 1,
                                "draws": 1,
                                "loses": 7
                            },
                            "wins": {
                                "home": "3-2",
                                "away": null
                            },
                            "loses": {
                                "home": "0-2",
                                "away": "4-0"
                            },
                            "goals": {
                                "for": {
                                    "home": 3,
                                    "away": 2
                                },
                                "against": {
                                    "home": 4,
                                    "away": 4
                                }
                            }
                        },
                        "clean_sheet": {
                            "home": 0,
                            "away": 2,
                            "total": 2
                        },
                        "failed_to_score": {
                            "home": 3,
                            "away": 5,
                            "total": 8
                        },
                        "penalty": {
                            "scored": {
                                "total": 0,
                                "percentage": "0%"
                            },
                            "missed": {
                                "total": 0,
                                "percentage": "0%"
                            },
                            "total": 0
                        },
                        "lineups": [],
                        "cards": {
                            "yellow": {
                                "0-15": {
                                    "total": null,
                                    "percentage": null
                                },
                                "16-30": {
                                    "total": null,
                                    "percentage": null
                                },
                                "31-45": {
                                    "total": null,
                                    "percentage": null
                                },
                                "46-60": {
                                    "total": null,
                                    "percentage": null
                                },
                                "61-75": {
                                    "total": null,
                                    "percentage": null
                                },
                                "76-90": {
                                    "total": null,
                                    "percentage": null
                                },
                                "91-105": {
                                    "total": null,
                                    "percentage": null
                                },
                                "106-120": {
                                    "total": null,
                                    "percentage": null
                                }
                            },
                            "red": {
                                "0-15": {
                                    "total": null,
                                    "percentage": null
                                },
                                "16-30": {
                                    "total": null,
                                    "percentage": null
                                },
                                "31-45": {
                                    "total": null,
                                    "percentage": null
                                },
                                "46-60": {
                                    "total": null,
                                    "percentage": null
                                },
                                "61-75": {
                                    "total": null,
                                    "percentage": null
                                },
                                "76-90": {
                                    "total": null,
                                    "percentage": null
                                },
                                "91-105": {
                                    "total": null,
                                    "percentage": null
                                },
                                "106-120": {
                                    "total": null,
                                    "percentage": null
                                }
                            }
                        }
                    }
                }
            },
            "comparison": {
                "form": {
                    "home": "29%",
                    "away": "71%"
                },
                "att": {
                    "home": "33%",
                    "away": "67%"
                },
                "def": {
                    "home": "44%",
                    "away": "56%"
                },
                "poisson_distribution": {
                    "home": "81%",
                    "away": "19%"
                },
                "h2h": {
                    "home": "75%",
                    "away": "25%"
                },
                "goals": {
                    "home": "60%",
                    "away": "40%"
                },
                "total": {
                    "home": "53.7%",
                    "away": "46.3%"
                }
            },
            "h2h": [
                {
                    "fixture": {
                        "id": 1275387,
                        "referee": null,
                        "timezone": "UTC",
                        "date": "2024-11-05T13:00:00+00:00",
                        "timestamp": 1730811600,
                        "periods": {
                            "first": 1730811600,
                            "second": 1730815200
                        },
                        "venue": {
                            "id": 20035,
                            "name": "Kigali Pel\u00e9 Stadium",
                            "city": "Kigali"
                        },
                        "status": {
                            "long": "Match Finished",
                            "short": "FT",
                            "elapsed": 90,
                            "extra": null
                        }
                    },
                    "league": {
                        "id": 405,
                        "name": "National Soccer League",
                        "country": "Rwanda",
                        "logo": "https://media.api-sports.io/football/leagues/405.png",
                        "flag": "https://media.api-sports.io/flags/rw.svg",
                        "season": 2024,
                        "round": "Regular Season - 9",
                        "standings": true
                    },
                    "teams": {
                        "home": {
                            "id": 5317,
                            "name": "Kiyovu Sports",
                            "logo": "https://media.api-sports.io/football/teams/5317.png",
                            "winner": false
                        },
                        "away": {
                            "id": 7574,
                            "name": "Gasogi United",
                            "logo": "https://media.api-sports.io/football/teams/7574.png",
                            "winner": true
                        }
                    },
                    "goals": {
                        "home": 3,
                        "away": 4
                    },
                    "score": {
                        "halftime": {
                            "home": null,
                            "away": null
                        },
                        "fulltime": {
                            "home": 3,
                            "away": 4
                        },
                        "extratime": {
                            "home": null,
                            "away": null
                        },
                        "penalty": {
                            "home": null,
                            "away": null
                        }
                    }
                },
                {
                    "fixture": {
                        "id": 1170902,
                        "referee": null,
                        "timezone": "UTC",
                        "date": "2024-02-03T13:00:00+00:00",
                        "timestamp": 1706965200,
                        "periods": {
                            "first": 1706965200,
                            "second": 1706968800
                        },
                        "venue": {
                            "id": 20035,
                            "name": "Kigali Pel\u00e9 Stadium",
                            "city": "Kigali"
                        },
                        "status": {
                            "long": "Match Finished",
                            "short": "FT",
                            "elapsed": 90,
                            "extra": null
                        }
                    },
                    "league": {
                        "id": 405,
                        "name": "National Soccer League",
                        "country": "Rwanda",
                        "logo": "https://media.api-sports.io/football/leagues/405.png",
                        "flag": "https://media.api-sports.io/flags/rw.svg",
                        "season": 2023,
                        "round": "Regular Season - 19",
                        "standings": true
                    },
                    "teams": {
                        "home": {
                            "id": 5317,
                            "name": "Kiyovu Sports",
                            "logo": "https://media.api-sports.io/football/teams/5317.png",
                            "winner": null
                        },
                        "away": {
                            "id": 7574,
                            "name": "Gasogi United",
                            "logo": "https://media.api-sports.io/football/teams/7574.png",
                            "winner": null
                        }
                    },
                    "goals": {
                        "home": 1,
                        "away": 1
                    },
                    "score": {
                        "halftime": {
                            "home": null,
                            "away": null
                        },
                        "fulltime": {
                            "home": 1,
                            "away": 1
                        },
                        "extratime": {
                            "home": null,
                            "away": null
                        },
                        "penalty": {
                            "home": null,
                            "away": null
                        }
                    }
                },
                {
                    "fixture": {
                        "id": 1114044,
                        "referee": null,
                        "timezone": "UTC",
                        "date": "2023-09-15T13:00:00+00:00",
                        "timestamp": 1694782800,
                        "periods": {
                            "first": 1694782800,
                            "second": 1694786400
                        },
                        "venue": {
                            "id": 20035,
                            "name": "Kigali Pel\u00e9 Stadium",
                            "city": "Kigali"
                        },
                        "status": {
                            "long": "Match Finished",
                            "short": "FT",
                            "elapsed": 90,
                            "extra": null
                        }
                    },
                    "league": {
                        "id": 405,
                        "name": "National Soccer League",
                        "country": "Rwanda",
                        "logo": "https://media.api-sports.io/football/leagues/405.png",
                        "flag": "https://media.api-sports.io/flags/rw.svg",
                        "season": 2023,
                        "round": "Regular Season - 4",
                        "standings": true
                    },
                    "teams": {
                        "home": {
                            "id": 7574,
                            "name": "Gasogi United",
                            "logo": "https://media.api-sports.io/football/teams/7574.png",
                            "winner": null
                        },
                        "away": {
                            "id": 5317,
                            "name": "Kiyovu Sports",
                            "logo": "https://media.api-sports.io/football/teams/5317.png",
                            "winner": null
                        }
                    },
                    "goals": {
                        "home": 1,
                        "away": 1
                    },
                    "score": {
                        "halftime": {
                            "home": null,
                            "away": null
                        },
                        "fulltime": {
                            "home": 1,
                            "away": 1
                        },
                        "extratime": {
                            "home": null,
                            "away": null
                        },
                        "penalty": {
                            "home": null,
                            "away": null
                        }
                    }
                },
                {
                    "fixture": {
                        "id": 933368,
                        "referee": null,
                        "timezone": "UTC",
                        "date": "2023-01-20T13:30:00+00:00",
                        "timestamp": 1674221400,
                        "periods": {
                            "first": 1674221400,
                            "second": 1674225000
                        },
                        "venue": {
                            "id": 4014,
                            "name": "Bugesera Stadium",
                            "city": "Nyamata"
                        },
                        "status": {
                            "long": "Match Finished",
                            "short": "FT",
                            "elapsed": 90,
                            "extra": null
                        }
                    },
                    "league": {
                        "id": 405,
                        "name": "National Soccer League",
                        "country": "Rwanda",
                        "logo": "https://media.api-sports.io/football/leagues/405.png",
                        "flag": "https://media.api-sports.io/flags/rw.svg",
                        "season": 2022,
                        "round": "Regular Season - 16",
                        "standings": true
                    },
                    "teams": {
                        "home": {
                            "id": 7574,
                            "name": "Gasogi United",
                            "logo": "https://media.api-sports.io/football/teams/7574.png",
                            "winner": null
                        },
                        "away": {
                            "id": 5317,
                            "name": "Kiyovu Sports",
                            "logo": "https://media.api-sports.io/football/teams/5317.png",
                            "winner": null
                        }
                    },
                    "goals": {
                        "home": 0,
                        "away": 0
                    },
                    "score": {
                        "halftime": {
                            "home": 0,
                            "away": 0
                        },
                        "fulltime": {
                            "home": 0,
                            "away": 0
                        },
                        "extratime": {
                            "home": null,
                            "away": null
                        },
                        "penalty": {
                            "home": null,
                            "away": null
                        }
                    }
                },
                {
                    "fixture": {
                        "id": 933325,
                        "referee": null,
                        "timezone": "UTC",
                        "date": "2022-11-27T13:00:00+00:00",
                        "timestamp": 1669554000,
                        "periods": {
                            "first": 1669554000,
                            "second": 1669557600
                        },
                        "venue": {
                            "id": 4012,
                            "name": "Stade R\u00e9gional de Nyamirambo",
                            "city": "Kigali"
                        },
                        "status": {
                            "long": "Match Finished",
                            "short": "FT",
                            "elapsed": 90,
                            "extra": null
                        }
                    },
                    "league": {
                        "id": 405,
                        "name": "National Soccer League",
                        "country": "Rwanda",
                        "logo": "https://media.api-sports.io/football/leagues/405.png",
                        "flag": "https://media.api-sports.io/flags/rw.svg",
                        "season": 2022,
                        "round": "Regular Season - 11",
                        "standings": true
                    },
                    "teams": {
                        "home": {
                            "id": 5317,
                            "name": "Kiyovu Sports",
                            "logo": "https://media.api-sports.io/football/teams/5317.png",
                            "winner": false
                        },
                        "away": {
                            "id": 7574,
                            "name": "Gasogi United",
                            "logo": "https://media.api-sports.io/football/teams/7574.png",
                            "winner": true
                        }
                    },
                    "goals": {
                        "home": 1,
                        "away": 3
                    },
                    "score": {
                        "halftime": {
                            "home": 0,
                            "away": 1
                        },
                        "fulltime": {
                            "home": 1,
                            "away": 3
                        },
                        "extratime": {
                            "home": null,
                            "away": null
                        },
                        "penalty": {
                            "home": null,
                            "away": null
                        }
                    }
                },
                {
                    "fixture": {
                        "id": 839653,
                        "referee": null,
                        "timezone": "UTC",
                        "date": "2022-04-15T13:00:00+00:00",
                        "timestamp": 1650027600,
                        "periods": {
                            "first": 1650027600,
                            "second": 1650031200
                        },
                        "venue": {
                            "id": 4012,
                            "name": "Stade R\u00e9gional de Nyamirambo",
                            "city": "Kigali"
                        },
                        "status": {
                            "long": "Match Finished",
                            "short": "FT",
                            "elapsed": 90,
                            "extra": null
                        }
                    },
                    "league": {
                        "id": 405,
                        "name": "National Soccer League",
                        "country": "Rwanda",
                        "logo": "https://media.api-sports.io/football/leagues/405.png",
                        "flag": "https://media.api-sports.io/flags/rw.svg",
                        "season": 2021,
                        "round": "Regular Season - 23",
                        "standings": true
                    },
                    "teams": {
                        "home": {
                            "id": 7574,
                            "name": "Gasogi United",
                            "logo": "https://media.api-sports.io/football/teams/7574.png",
                            "winner": true
                        },
                        "away": {
                            "id": 5317,
                            "name": "Kiyovu Sports",
                            "logo": "https://media.api-sports.io/football/teams/5317.png",
                            "winner": false
                        }
                    },
                    "goals": {
                        "home": 2,
                        "away": 0
                    },
                    "score": {
                        "halftime": {
                            "home": 1,
                            "away": 0
                        },
                        "fulltime": {
                            "home": 2,
                            "away": 0
                        },
                        "extratime": {
                            "home": null,
                            "away": null
                        },
                        "penalty": {
                            "home": null,
                            "away": null
                        }
                    }
                },
                {
                    "fixture": {
                        "id": 807114,
                        "referee": null,
                        "timezone": "UTC",
                        "date": "2021-12-12T10:30:00+00:00",
                        "timestamp": 1639305000,
                        "periods": {
                            "first": 1639305000,
                            "second": 1639308600
                        },
                        "venue": {
                            "id": 4012,
                            "name": "Stade R\u00e9gional de Nyamirambo",
                            "city": "Kigali"
                        },
                        "status": {
                            "long": "Match Finished",
                            "short": "FT",
                            "elapsed": 90,
                            "extra": null
                        }
                    },
                    "league": {
                        "id": 405,
                        "name": "National Soccer League",
                        "country": "Rwanda",
                        "logo": "https://media.api-sports.io/football/leagues/405.png",
                        "flag": "https://media.api-sports.io/flags/rw.svg",
                        "season": 2021,
                        "round": "Regular Season - 8",
                        "standings": true
                    },
                    "teams": {
                        "home": {
                            "id": 5317,
                            "name": "Kiyovu Sports",
                            "logo": "https://media.api-sports.io/football/teams/5317.png",
                            "winner": null
                        },
                        "away": {
                            "id": 7574,
                            "name": "Gasogi United",
                            "logo": "https://media.api-sports.io/football/teams/7574.png",
                            "winner": null
                        }
                    },
                    "goals": {
                        "home": 1,
                        "away": 1
                    },
                    "score": {
                        "halftime": {
                            "home": 1,
                            "away": 1
                        },
                        "fulltime": {
                            "home": 1,
                            "away": 1
                        },
                        "extratime": {
                            "home": null,
                            "away": null
                        },
                        "penalty": {
                            "home": null,
                            "away": null
                        }
                    }
                },
                {
                    "fixture": {
                        "id": 705504,
                        "referee": null,
                        "timezone": "UTC",
                        "date": "2021-06-28T13:00:00+00:00",
                        "timestamp": 1624885200,
                        "periods": {
                            "first": 1624885200,
                            "second": 1624888800
                        },
                        "venue": {
                            "id": 4014,
                            "name": "Bugesera Stadium",
                            "city": "Nyamata"
                        },
                        "status": {
                            "long": "Match Finished",
                            "short": "FT",
                            "elapsed": 90,
                            "extra": null
                        }
                    },
                    "league": {
                        "id": 405,
                        "name": "National Soccer League",
                        "country": "Rwanda",
                        "logo": "https://media.api-sports.io/football/leagues/405.png",
                        "flag": "https://media.api-sports.io/flags/rw.svg",
                        "season": 2020,
                        "round": "Lower Table Round - 7",
                        "standings": true
                    },
                    "teams": {
                        "home": {
                            "id": 7574,
                            "name": "Gasogi United",
                            "logo": "https://media.api-sports.io/football/teams/7574.png",
                            "winner": true
                        },
                        "away": {
                            "id": 5317,
                            "name": "Kiyovu Sports",
                            "logo": "https://media.api-sports.io/football/teams/5317.png",
                            "winner": false
                        }
                    },
                    "goals": {
                        "home": 1,
                        "away": 0
                    },
                    "score": {
                        "halftime": {
                            "home": null,
                            "away": null
                        },
                        "fulltime": {
                            "home": 1,
                            "away": 0
                        },
                        "extratime": {
                            "home": null,
                            "away": null
                        },
                        "penalty": {
                            "home": null,
                            "away": null
                        }
                    }
                },
                {
                    "fixture": {
                        "id": 699680,
                        "referee": null,
                        "timezone": "UTC",
                        "date": "2021-05-11T13:00:00+00:00",
                        "timestamp": 1620738000,
                        "periods": {
                            "first": 1620738000,
                            "second": 1620741600
                        },
                        "venue": {
                            "id": 4019,
                            "name": "Stade Mumena",
                            "city": "Kigali"
                        },
                        "status": {
                            "long": "Match Finished",
                            "short": "FT",
                            "elapsed": 90,
                            "extra": null
                        }
                    },
                    "league": {
                        "id": 405,
                        "name": "National Soccer League",
                        "country": "Rwanda",
                        "logo": "https://media.api-sports.io/football/leagues/405.png",
                        "flag": "https://media.api-sports.io/flags/rw.svg",
                        "season": 2020,
                        "round": "Group Stage - 4",
                        "standings": true
                    },
                    "teams": {
                        "home": {
                            "id": 5317,
                            "name": "Kiyovu Sports",
                            "logo": "https://media.api-sports.io/football/teams/5317.png",
                            "winner": true
                        },
                        "away": {
                            "id": 7574,
                            "name": "Gasogi United",
                            "logo": "https://media.api-sports.io/football/teams/7574.png",
                            "winner": false
                        }
                    },
                    "goals": {
                        "home": 4,
                        "away": 1
                    },
                    "score": {
                        "halftime": {
                            "home": null,
                            "away": null
                        },
                        "fulltime": {
                            "home": 4,
                            "away": 1
                        },
                        "extratime": {
                            "home": null,
                            "away": null
                        },
                        "penalty": {
                            "home": null,
                            "away": null
                        }
                    }
                },
                {
                    "fixture": {
                        "id": 699670,
                        "referee": null,
                        "timezone": "UTC",
                        "date": "2021-05-08T10:30:00+00:00",
                        "timestamp": 1620469800,
                        "periods": {
                            "first": 1620469800,
                            "second": 1620473400
                        },
                        "venue": {
                            "id": 4014,
                            "name": "Bugesera Stadium",
                            "city": "Nyamata"
                        },
                        "status": {
                            "long": "Match Finished",
                            "short": "FT",
                            "elapsed": 90,
                            "extra": null
                        }
                    },
                    "league": {
                        "id": 405,
                        "name": "National Soccer League",
                        "country": "Rwanda",
                        "logo": "https://media.api-sports.io/football/leagues/405.png",
                        "flag": "https://media.api-sports.io/flags/rw.svg",
                        "season": 2020,
                        "round": "Group Stage - 3",
                        "standings": true
                    },
                    "teams": {
                        "home": {
                            "id": 7574,
                            "name": "Gasogi United",
                            "logo": "https://media.api-sports.io/football/teams/7574.png",
                            "winner": true
                        },
                        "away": {
                            "id": 5317,
                            "name": "Kiyovu Sports",
                            "logo": "https://media.api-sports.io/football/teams/5317.png",
                            "winner": false
                        }
                    },
                    "goals": {
                        "home": 2,
                        "away": 1
                    },
                    "score": {
                        "halftime": {
                            "home": null,
                            "away": null
                        },
                        "fulltime": {
                            "home": 2,
                            "away": 1
                        },
                        "extratime": {
                            "home": null,
                            "away": null
                        },
                        "penalty": {
                            "home": null,
                            "away": null
                        }
                    }
                }
            ]
        }
    ],
    "mutual": {
        "away": {
            "guest_vs_home": {
                "match": {
                    "guest_name": {},
                    "home_name": {}
                },
                "guest_data": {},
                "guest_ratings": {},
                "home_data": {},
                "home_ratings": {}
            },
            "guest_vs_away": {
                "match": {
                    "guest_name": {},
                    "away_name": {}
                },
                "guest_data": {},
                "guest_ratings": {},
                "away_data": {},
                "away_ratings": {}
            }
        },
        "home": {
            "home_vs_guest": {
                "match": {
                    "home_name": {},
                    "guest_name": {}
                },
                "home_data": {},
                "home_ratings": {},
                "guest_data": {},
                "guest_ratings": {}
            },
            "away_vs_guest": {
                "match": {
                    "away_name": {},
                    "guest_name": {}
                },
                "away_data": {},
                "away_ratings": {},
                "guest_data": {},
                "guest_ratings": {}
            }
        }
    }
}